supplychain_demo/__init__.py
supplychain_demo/cli.py
request_fake_demo-0.0.1.dist-info/METADATA
request_fake_demo-0.0.1.dist-info/WHEEL
request_fake_demo-0.0.1.dist-info/entry_points.txt
request_fake_demo-0.0.1.dist-info/top_level.txt
request_fake_demo-0.0.1.dist-info/RECORD
