Metadata-Version: 2.4
Name: request_fake_demo
Version: 0.0.1
Summary: Safe demo package to show import-time code execution (harmless)
Author: A1fredx
License: MIT
